{"cameraMode":{"drawMode":0,"name":"Shaded","section":"Shading Mode"},"sceneLighting":true,"audioPlay":false,"sceneViewState":{"showFog":true,"showMaterialUpdate":false,"showSkybox":true,"showFlares":true,"showImageEffects":true,"showParticleSystems":true},"in2DMode":false,"pivot":{"x":-9.213933944702149,"y":13.414612770080567,"z":0.9481265544891357},"rotation":{"x":-0.09526587277650833,"y":0.8674603700637817,"z":-0.1824541985988617,"w":-0.452932208776474},"size":57.140037536621097,"orthographic":false}